LICENSE
README.md
pyproject.toml
src/fenicsx_ii/__init__.py
src/fenicsx_ii/assembly.py
src/fenicsx_ii/interpolation.py
src/fenicsx_ii/interpolation_utils.py
src/fenicsx_ii/matrix_assembler.py
src/fenicsx_ii/quadrature.py
src/fenicsx_ii/restriction_operators.py
src/fenicsx_ii/solver.py
src/fenicsx_ii/ufl_operations.py
src/fenicsx_ii/utils.py
src/fenicsx_ii/vector_assembler.py
src/fenicsx_ii.egg-info/PKG-INFO
src/fenicsx_ii.egg-info/SOURCES.txt
src/fenicsx_ii.egg-info/dependency_links.txt
src/fenicsx_ii.egg-info/requires.txt
src/fenicsx_ii.egg-info/top_level.txt
tests/test_average_coefficient.py
tests/test_circle_quadrature.py
tests/test_interpolation_matrix.py