Metadata-Version: 2.4
Name: fenicsx_ii
Version: 0.3.0
Summary: Mixed-dimensional coupling in FEniCSx
Author-email: "Jørgen S. Dokken" <dokken@simula.no>
License: MIT License
License-File: LICENSE
Requires-Dist: fenics-dolfinx<0.11.0,>=0.10.0
Provides-Extra: test
Requires-Dist: pytest; extra == "test"
Requires-Dist: sympy; extra == "test"
Provides-Extra: dev
Requires-Dist: pdbpp; extra == "dev"
Requires-Dist: ipython; extra == "dev"
Requires-Dist: mypy; extra == "dev"
Requires-Dist: ruff; extra == "dev"
Provides-Extra: docs
Requires-Dist: jupyter-book; extra == "docs"
Requires-Dist: jupytext; extra == "docs"
Requires-Dist: sphinx-codeautolink; extra == "docs"
Provides-Extra: jupyter
Requires-Dist: trame_jupyter_extension; extra == "jupyter"
Requires-Dist: trame; extra == "jupyter"
Requires-Dist: pyvista[all]>=0.45.0; extra == "jupyter"
Provides-Extra: all
Requires-Dist: fenicsx_ii[test]; extra == "all"
Requires-Dist: fenicsx_ii[dev]; extra == "all"
Requires-Dist: fenicsx_ii[docs]; extra == "all"
Requires-Dist: fenicsx_ii[jupyter]; extra == "all"
Dynamic: license-file
